{"/etc/issue.net":"Linux Mint 21.3 Virginia","antiFeatures":{},"apksigner":"/usr/bin/apksigner","archivePolicy0":[],"commandLine":["/home/gordon/.local/bin/fdroid update"],"disabled":[],"endTimestamp":1761339610572,"failedBuilds":{"de.ax12.zunclock":[200]},"jarsigner":"/usr/lib/jvm/java-17-openjdk-amd64/bin/jarsigner","keytool":"/usr/lib/jvm/java-17-openjdk-amd64/bin/keytool","needsUpdate":["de.ax12.zunclock"],"noPackages":["de.ax12.zunclock"],"noUpdateCheck":["de.ax12.zunclock"],"stages":{"delete_disabled_builds":1761339608076,"index.make repo":1761339608085,"prepare_apps repo":1761339608082,"process_apks":1761339608081,"read_added_date_from_all_apks":1761339608082,"remove_apks":1761339608082,"scan_repo_files":1761339608082},"startTimestamp":1761336008000,"subcommand":"update"}